rosonic/__init__.py
rosonic/argument.py
rosonic/container.py
rosonic/name.py
rosonic/node.py
rosonic/on_shutdown.py
rosonic/parameter.py
rosonic/timer.py
rosonic-0.2.2.dist-info/METADATA
rosonic-0.2.2.dist-info/WHEEL
rosonic-0.2.2.dist-info/top_level.txt
rosonic-0.2.2.dist-info/RECORD
