Metadata-Version: 2.1
Name: rosonic
Version: 0.2.2
Summary: Write pythonic ROS nodes, fast and comfortably
Home-page: https://kaarmu.github.io/rosonic/
Author: Kaj Munhoz Arfvidsson
Author-email: kajarf@kth.se
License: MIT
Provides: rosonic
Requires-Python: >=2.7
Provides-Extra: docs
Requires-Dist: mkdocs ; extra == 'docs'
Requires-Dist: mkdocs-with-pdf ; extra == 'docs'
